deciphon_poster/__init__.py
deciphon_poster/errors.py
deciphon_poster/poster.py
deciphon_poster/schema.py
deciphon_poster-0.2.4.dist-info/METADATA
deciphon_poster-0.2.4.dist-info/WHEEL
deciphon_poster-0.2.4.dist-info/RECORD
